jaxitude/__init__.py
jaxitude/base.py
jaxitude/eulerangles.py
jaxitude/prv.py
jaxitude/quaternions.py
jaxitude/rodrigues.py
jaxitude/determination/__init__.py
jaxitude/determination/davenport.py
jaxitude/determination/olae.py
jaxitude/determination/quest.py
jaxitude/determination/triad.py
jaxitude/estimation/__init__.py
jaxitude/estimation/ekf.py
jaxitude/operations/__init__.py
jaxitude/operations/error.py
jaxitude/operations/evolution.py
jaxitude/operations/integrator.py
jaxitude/operations/linearization.py
jaxitude/operations/transformation.py
jaxitude-1.0.0.dist-info/LICENSE
jaxitude-1.0.0.dist-info/METADATA
jaxitude-1.0.0.dist-info/WHEEL
jaxitude-1.0.0.dist-info/top_level.txt
jaxitude-1.0.0.dist-info/RECORD
