Metadata-Version: 2.1
Name: jaxitude
Version: 1.0.0
Summary: Intuitive attitude calculations, conversions, and state estimation modeling with JAX
Author: jhand1993
Project-URL: Homepage, https://github.com/jhand1993/jaxitude
Project-URL: Bug Tracker, https://github.com/jhand/jaxitude/issues
Classifier: Programming Language :: Python :: 3
Classifier: License :: OSI Approved :: MIT License
Classifier: Operating System :: OS Independent
Requires-Python: >=3.9.18
License-File: LICENSE
